nonebot_plugin_random_choice/__init__.py
nonebot_plugin_random_choice/config.py
nonebot_plugin_random_choice-0.1.0.dist-info/METADATA
nonebot_plugin_random_choice-0.1.0.dist-info/WHEEL
nonebot_plugin_random_choice-0.1.0.dist-info/top_level.txt
nonebot_plugin_random_choice-0.1.0.dist-info/RECORD
